[
  {
    "id": "dismiss_fire_ter",
    "type": "ter_furn_transform",
    "field": [
      { 
        "valid_field": [ "fd_fire", "fd_incendiary", "fd_flame_burst" ], 
        "result": "fd_null", 
        "message": "The fires goes away."
      }
    ]
  },
  {
    "id": "groundmelt_ter",
    "type": "ter_furn_transform",
    "terrain": [
      { 
        "valid_flags": [ "DIGGABLE", "MINEABLE" ], 
        "result": "t_lava", 
        "message": "The ground heats up and turns into lava!" 
      }
    ]
  },
  {
    "id": "keystone_crash_fur",
    "type": "ter_furn_transform",
    "furniture": [
      {
        "valid_flags": [ "EASY_DECONSTRUCT", "FLAMMABLE", "FLAMMABLE_ASH", "FLAMMABLE_HARD", "MINEABLE", "TRANSPARENT" ], 
        "result": "f_keystone", 
        "message": "A keystone materializes and crashes down!" 
      }
    ]
  },
  {
    "id": "keystone_dismiss_fur",
    "type": "ter_furn_transform",
    "furniture": [
      {
        "valid_furniture": [ "f_keystone", "f_keystone_pillar", "f_rubble" ], 
        "result": "f_null", 
        "message": "The earth obeys your command." 
      }
    ]
  },
  {
    "id": "keystone_pillar_fur",
    "type": "ter_furn_transform",
    "furniture": [
      {
        "valid_flags": [ "DIGGABLE", "EASY_DECONSTRUCT", "FLAMMABLE", "FLAMMABLE_ASH", "FLAMMABLE_HARD", "MINEABLE", "TRANSPARENT" ], 
        "result": "f_keystone_pillar", 
        "message": "A pillar keystone materializes and comes from the ground!" 
      }
    ]
  },
  {
    "id": "nukeglassing_ter",
    "type": "ter_furn_transform",
    "terrain": [ 
      { 
        "valid_flags": [ "DIGGABLE" ], 
        "result": "t_glassed_sand" 
      } 
    ]
  },
  {
    "id": "web_bridge_fur",
    "type": "ter_furn_transform",
    "furniture": [ 
      { 
        "valid_flags": [ "NO_FLOOR", "TRANSPARENT" ], 
        "result": "f_web_bridge"
      } 
    ]
  },
  {
    "id": "web_dismiss_terfur",
    "type": "ter_furn_transform",
    "field": [
      { 
        "valid_field": [ "fd_web", "fd_web2", "fd_web3" ], 
        "result": "fd_null", 
        "message": "Webs around you disintegrate.", 
        "message_good": true 
      }
    ],
    "furniture": [ { "result": "f_null", "message": "Webs around you disintegrate.", "valid_furniture": [ "f_web_up" ] } ]
  },
  {
    "id": "web_rappel_fur",
    "type": "ter_furn_transform",
    "furniture": [ 
      { 
        "valid_flags": [ "NO_FLOOR" ], 
        "result": "f_web_rappel"
      } 
    ]
  }
]
